{
  "project_info": {
    "project_number": "812420303292",
    "project_id": "democapacitorpushnotifications",
    "storage_bucket": "democapacitorpushnotifications.appspot.com"
  },
  "client": [
    {
      "client_info": {
        "mobilesdk_app_id": "1:812420303292:android:52a1b73d371a19c33003b9",
        "android_client_info": {
          "package_name": "com.example.app"
        }
      },
      "oauth_client": [
        {
          "client_id": "812420303292-2507h6npp5vi7m4f4pvcth6ku0lnp3vb.apps.googleusercontent.com",
          "client_type": 3
        }
      ],
      "api_key": [
        {
          "current_key": "AIzaSyBP85w5W0ZIxn8j8JMVMkRSi46SIq0I7KU"
        }
      ],
      "services": {
        "appinvite_service": {
          "other_platform_oauth_client": [
            {
              "client_id": "812420303292-2507h6npp5vi7m4f4pvcth6ku0lnp3vb.apps.googleusercontent.com",
              "client_type": 3
            }
          ]
        }
      }
    }
  ],
  "configuration_version": "1"
}